MonoCipher/__init__.py
MonoCipher/test.py
MonoCipher/ByteEncryption/__init__.py
MonoCipher/HmacEncryption/__init__.py
MonoCipher/MacEncryption/__init__.py
MonoCipher/NonceEncryption/__init__.py
MonoCipher/SaltEncryption/__init__.py
MonoCipher/SimpleEncryption/__init__.py
MonoCipher-0.1.3.dist-info/LICENCE
MonoCipher-0.1.3.dist-info/METADATA
MonoCipher-0.1.3.dist-info/WHEEL
MonoCipher-0.1.3.dist-info/entry_points.txt
MonoCipher-0.1.3.dist-info/top_level.txt
MonoCipher-0.1.3.dist-info/RECORD
