Metadata-Version: 2.1
Name: MonoCipher
Version: 0.1.3
Summary: A package for monoalphabetic ciphers (message encryption and decryption).
Home-page: https://github.com/rakeshkanna-rk/MonoCipher
Author: Rakesh Kanna
Author-email: rakeshkanna0108@gmail.com
License: MIT
Project-URL: GitHub, https://github.com/rakeshkanna-rk/MonoCipher/
Project-URL: PyPI, https://pypi.org/project/MonoCipher/
Keywords: encryption,cryptography,security
Classifier: Programming Language :: Python :: 3
Classifier: License :: OSI Approved :: MIT License
Classifier: Operating System :: OS Independent
Requires-Python: >=3.6
License-File: LICENCE
Requires-Dist: pycryptodome >=3.20.0
Requires-Dist: tqdm
